{
  "lastUpdated": "2026-03-25T16:33:48.354Z",
  "texts": [
    {
      "id": "reading-001",
      "title": "Asunnon etsiminen",
      "level": "B1",
      "text": "Etsin uutta asuntoa Helsingin keskustasta...",
      "translation": "I am looking for a new apartment...",
      "keywords": [
        "asunto",
        "vuokra",
        "yksiö"
      ],
      "questions": [
        {
          "id": "q1",
          "type": "multiple-choice",
          "question": "Mitä henkilö etsii?",
          "options": [
            "Taloa",
            "Yksiötä",
            "Kaksiota"
          ],
          "correct": 1
        }
      ],
      "state": "new",
      "usedInExam": false,
      "source": "github",
      "createdAt": "2026-01-15T00:00:00.000Z"
    },
    {
      "id": "user-1774453802594",
      "title": "Kirjasto on kiva paikka",
      "level": "B1",
      "text": "Oletko käynyt kotipaikkakuntasi kirjastossa? Tiedätkö, mitä kirjastossa tehdään?\nKirjastosta voi lainata kirjoja, CD-levyjä, DVD-elokuvia ja lehtiä. Joistakin kirjastoista voi jopa lainata tavaroita, kuten ompelukoneita, kitaroita, porakoneita ja ulkopelejä!\nKirjasto on monille ihmisille kuin toinen olohuone. He viettävät siellä aikaansa, lukevat, opiskelevat tai työskentelevät. Siellä voi käyttää myös tietokonetta ja internetiä.\nKirjastossa on myös erilaisia tapahtumia. Siellä voi kokoontua lukupiiri. Joissakin kirjastoissa järjestetään suomen kielen keskustelukerhoja maahanmuuttajille. Joissakin kirjastoissa lapset voivat osallistua koulun jälkeen läksykerhoon. Siellä joku aikuinen auttaa lapsia läksyjen tekemisessä.\nJos haluat lainata kirjastosta jotain kotiin, tarvitset kirjastokortin. Se ei maksa mitään. Voit kysyä sitä kirjaston henkilökunnalta. Ota silloin mukaan henkilöllisyystodistus.",
      "keywords": [],
      "questions": [],
      "state": "new",
      "usedInExam": false,
      "source": "user",
      "createdAt": "2026-03-25T15:50:02.595Z"
    },
    {
      "id": "user-1774456421537",
      "title": "Vuokrasopimuksen allekirjoitus",
      "level": "B1",
      "text": "Maryamille on tarjottu vuokra-asuntoa. Hän on käynyt katsomassa sitä perheensä kanssa. Asunto on suurempi kuin heidän nykyinen asuntonsa. Koko perhe on tyytyväinen uuteen asuntoon, sillä se on lähellä Maryamin työpaikkaa ja hänen poikansa koulua. Tänään Maryam ja hänen miehensä Max menevät allekirjoittamaan vuokrasopimuksen.\nVuokrasopimuksessa on määritelty vuokran määrä ja sopimuksen kesto. Maryamin ja Maxin vuokrasopimus on toistaiseksi voimassa. Se tarkoittaa, että heidän sopimuksensa jatkuu, kunnes he päättävät irtisanoa sen. Myös vuokranantaja voi irtisanoa sopimuksen.\nHeidän täytyy myös maksaa takuuvuokra. Se on kolmen kuukauden vuokra. He saavat takuuvuokran takaisin, jos asunto on hyvässä kunnossa, kun he muuttavat pois.",
      "keywords": [],
      "questions": [],
      "state": "new",
      "usedInExam": false,
      "source": "user",
      "createdAt": "2026-03-25T16:33:41.537Z"
    }
  ]
}